mwpf_fast-0.2.12.dist-info/RECORD
mwpf_fast-0.2.12.dist-info/METADATA
mwpf_fast-0.2.12.dist-info/WHEEL
mwpf_fast-0.2.12.dist-info/licenses/LICENSE
mwpf_fast/mwpf_fast.abi3.so
mwpf_fast/heralded_dem.py
mwpf_fast/sinter_decoders.py
mwpf_fast/ref_circuit.py
mwpf_fast/__init__.py
