Metadata-Version: 2.4
Name: mwpf_fast
Version: 0.2.12
Classifier: Programming Language :: Rust
Classifier: Programming Language :: Python
Classifier: Programming Language :: Python :: 3
Classifier: Programming Language :: Python :: 3 :: Only
Classifier: Programming Language :: Python :: 3.8
Classifier: Programming Language :: Python :: 3.9
Classifier: Programming Language :: Python :: 3.10
Classifier: Programming Language :: Python :: 3.11
Classifier: Programming Language :: Python :: Implementation :: CPython
Classifier: Programming Language :: Python :: Implementation :: PyPy
Classifier: Intended Audience :: Developers
Classifier: Intended Audience :: Information Technology
Classifier: Intended Audience :: System Administrators
Classifier: License :: OSI Approved :: MIT License
Classifier: Operating System :: Unix
Classifier: Operating System :: POSIX :: Linux
Classifier: Environment :: Console
Classifier: Environment :: MacOS X
Classifier: Topic :: Software Development :: Libraries :: Python Modules
Classifier: Topic :: Internet
Requires-Dist: frozendict ; extra == 'stim'
Requires-Dist: frozenlist ; extra == 'stim'
Requires-Dist: numpy ; extra == 'stim'
Requires-Dist: stim>=1.14.0 ; extra == 'stim'
Requires-Dist: sinter>=1.14.0 ; extra == 'stim'
Provides-Extra: stim
License-File: LICENSE
Summary: Minimum-Weight Parity Factor (MWPF) decoder for QEC
Home-Page: https://hyper-mwpf.com
License-Expression: MIT
Requires-Python: >=3.8
